skaff_telemetry/__init__.py
skaff_telemetry/config.py
skaff_telemetry/decorator.py
skaff_telemetry-0.1.4.dist-info/LICENSE
skaff_telemetry-0.1.4.dist-info/METADATA
skaff_telemetry-0.1.4.dist-info/WHEEL
skaff_telemetry-0.1.4.dist-info/RECORD
