Metadata-Version: 2.1
Name: skaff-telemetry
Version: 0.1.4
Summary: Decorator for adding telemetry sending capability to functions.
Author: Alexis VIALARET
Author-email: alexis.vialaret@artefact.com
Requires-Python: >=3.10
Classifier: Programming Language :: Python :: 3
Classifier: Programming Language :: Python :: 3.10
Classifier: Programming Language :: Python :: 3.11
Classifier: Programming Language :: Python :: 3.12
Requires-Dist: requests (>=2.25,<3)
